lexical/__init__.py
lexical/_version.py
lexical/main.py
lexical/server.py
lexical/data/adj.exc
lexical/data/adv.exc
lexical/data/data.adj
lexical/data/data.adv
lexical/data/data.noun
lexical/data/data.verb
lexical/data/index.adj
lexical/data/index.adv
lexical/data/index.noun
lexical/data/index.verb
lexical/data/noun.exc
lexical/data/verb.exc
lexical/wordnet/__init__.py
lexical/wordnet/wordnet.py
lexical_server-1.0.1.dist-info/METADATA
lexical_server-1.0.1.dist-info/WHEEL
lexical_server-1.0.1.dist-info/entry_points.txt
lexical_server-1.0.1.dist-info/top_level.txt
lexical_server-1.0.1.dist-info/RECORD
