Metadata-Version: 2.4
Name: Lexical-Server
Version: 1.0.1
Summary: A dictionary server
Author-email: Chris Cochran <cochranschris@gmail.com>
Requires-Python: >=3.13
Provides-Extra: test
Requires-Dist: pytest; extra == "test"
